chlamys/__init__.py
chlamys-0.1.0.dist-info/AUTHORS.rst
chlamys-0.1.0.dist-info/LICENSE
chlamys-0.1.0.dist-info/METADATA
chlamys-0.1.0.dist-info/WHEEL
chlamys-0.1.0.dist-info/top_level.txt
chlamys-0.1.0.dist-info/RECORD
