Metadata-Version: 2.1
Name: chlamys
Version: 0.1.0
Summary: Smooth interpolation on scattered data with levels and slopes.
Home-page: https://github.com/dougmvieira/chlamys
Author: Douglas Machado Vieira
Author-email: dougmvieira@gmail.com
License: MIT license
Project-URL: Documentation, https://chlamys.readthedocs.io/
Project-URL: Changelog, https://chlamys.readthedocs.io/en/latest/changelog.html
Project-URL: Issue Tracker, https://github.com/dougmvieira/chlamys/issues
Platform: UNKNOWN
Classifier: Development Status :: 5 - Production/Stable
Classifier: Intended Audience :: Developers
Classifier: License :: OSI Approved :: MIT License
Classifier: Operating System :: Unix
Classifier: Operating System :: POSIX
Classifier: Operating System :: Microsoft :: Windows
Classifier: Programming Language :: Python
Classifier: Programming Language :: Python :: 2.7
Classifier: Programming Language :: Python :: 3
Classifier: Programming Language :: Python :: 3.5
Classifier: Programming Language :: Python :: 3.6
Classifier: Programming Language :: Python :: 3.7
Classifier: Programming Language :: Python :: Implementation :: CPython
Classifier: Topic :: Utilities
Requires-Python: >=2.7, !=3.0.*, !=3.1.*, !=3.2.*, !=3.3.*, !=3.4.*
Requires-Dist: numpy
Requires-Dist: sympy
Requires-Dist: scipy
